Workbook

Sheet Sheet1
A1: Indicateurs | B1: Importance | D1: Pondération random forest
A2: Ratio dette/PIB des ménages | B2: 0.099165414 | D2: 0.15527651
A3: Spread HY-Mid Swap | B3: 0.072286504 | D3: 0.11318862
A4: Debt Service Ratio des SNF | B4: 0.054159374 | D4: 0.084804555
A5: Croissance des prêts aux ménages | B5: 0.053832691 | D5: 0.084293023
A6: Ratio dette/PIB des SNF | B6: 0.051184027 | D6: 0.080145656
A7: Ratio prix de l'immobilier / revenus des ménages | B7: 0.046027534 | D7: 0.072071448
A8: Debt Service Ratio des ménages | B8: 0.043420646 | D8: 0.067989496
A9: Spread IG-Mid Swap | B9: 0.03322762 | D9: 0.052028917
A10: Croissance des prêts aux SNF | B10: 0.028356621 | D10: 0.044401744
A11: Taux d'intérêt moyen des nouveaux crédits aux ménages | B11: 0.02767795 | D11: 0.043339058
A12: Surévaluation des prix de l'immobilier (ISPI) | B12: 0.023789287 | D12: 0.037250059
A13: Durcissement des conditions d'octroi du crédit (% soldes d'opinion) – Entreprises (BLS) | B13: 0.02065031 | D13: 0.032334945
... A20: Spread OAT-Bund | B20: 0.0091823163 | D20: 0.014377977

Sheet Tableau
A1: Catégories | B1: Indicateurs | C1: Pondération | D1: Par catégorie | E1: Importance
A2: Encours de dette des ménages et SNF | B2: Ratio dette/PIB des ménages | C2: =_xlfn.XLOOKUP($B2, Sheet1!$A$2:$A$20, Sheet1!$D$2:$D$20) -> 0.15527651 | D2: =SUM(C2:C7) -> 0.51691099 | E2: =_xlfn.XLOOKUP($B2, Sheet1!$A$2:$A$20, Sheet1!$B$2:$B$20) -> 0.099165414
B3: Ratio dette/PIB des SNF | C3: =_xlfn.XLOOKUP($B3, Sheet1!$A$2:$A$20, Sheet1!$D$2:$D$20) -> 0.080145656 | E3: =_xlfn.XLOOKUP($B3, Sheet1!$A$2:$A$20, Sheet1!$B$2:$B$20) -> 0.051184027
B4: Croissance des prêts aux ménages | C4: =_xlfn.XLOOKUP($B4, Sheet1!$A$2:$A$20, Sheet1!$D$2:$D$20) -> 0.084293023 | E4: =_xlfn.XLOOKUP($B4, Sheet1!$A$2:$A$20, Sheet1!$B$2:$B$20) -> 0.053832691
B5: Croissance des prêts aux SNF | C5: =_xlfn.XLOOKUP($B5, Sheet1!$A$2:$A$20, Sheet1!$D$2:$D$20) -> 0.044401744 | E5: =_xlfn.XLOOKUP($B5, Sheet1!$A$2:$A$20, Sheet1!$B$2:$B$20) -> 0.028356621
B6: Debt Service Ratio des ménages | C6: =_xlfn.XLOOKUP($B6, Sheet1!$A$2:$A$20, Sheet1!$D$2:$D$20) -> 0.067989496 | E6: =_xlfn.XLOOKUP($B6, Sheet1!$A$2:$A$20, Sheet1!$B$2:$B$20) -> 0.043420646
B7: Debt Service Ratio des SNF | C7: =_xlfn.XLOOKUP($B7, Sheet1!$A$2:$A$20, Sheet1!$D$2:$D$20) -> 0.084804555 | E7: =_xlfn.XLOOKUP($B7, Sheet1!$A$2:$A$20, Sheet1!$B$2:$B$20) -> 0.054159374
A8: Conditions de financement du crédit | B8: Taux d'intérêt moyen des nouveaux crédits aux ménages | C8: =_xlfn.XLOOKUP($B8, Sheet1!$A$2:$A$20, Sheet1!$D$2:$D$20) -> 0.043339058 | D8: =SUM(C8:C12) -> 0.13629113 | E8: =_xlfn.XLOOKUP($B8, Sheet1!$A$2:$A$20, Sheet1!$B$2:$B$20) -> 0.02767795
B9: Taux d'intérêt moyen des nouveaux crédits aux SNF | C9: =_xlfn.XLOOKUP($B9, Sheet1!$A$2:$A$20, Sheet1!$D$2:$D$20) -> 0.020732836 | E9: =_xlfn.XLOOKUP($B9, Sheet1!$A$2:$A$20, Sheet1!$B$2:$B$20) -> 0.013240768
B10: Durcissement des conditions d'octroi du crédit (% soldes d'opinion) – Entreprises (BLS) | C10: =_xlfn.XLOOKUP($B10, Sheet1!$A$2:$A$20, Sheet1!$D$2:$D$20) -> 0.032334945 | E10: =_xlfn.XLOOKUP($B10, Sheet1!$A$2:$A$20, Sheet1!$B$2:$B$20) -> 0.02065031
B11: Durcissement des conditions d'octroi du crédit (% soldes d'opinion) – Ménages (BLS) | C11: =_xlfn.XLOOKUP($B11, Sheet1!$A$2:$A$20, Sheet1!$D$2:$D$20) -> 0.021231128 | E11: =_xlfn.XLOOKUP($B11, Sheet1!$A$2:$A$20, Sheet1!$B$2:$B$20) -> 0.013558996
B12: Part des SNF ayant des "contraintes de crédit" (% de réponses) (SAFE) | C12: =_xlfn.XLOOKUP($B12, Sheet1!$A$2:$A$20, Sheet1!$D$2:$D$20) -> 0.018653161 | E12: =_xlfn.XLOOKUP($B12, Sheet1!$A$2:$A$20, Sheet1!$B$2:$B$20) -> 0.011912609
A13: Marché immobilier | B13: Surévaluation des prix de l'immobilier (ISPI) | C13: =_xlfn.XLOOKUP($B13, Sheet1!$A$2:$A$20, Sheet1!$D$2:$D$20) -> 0.037250059 | D13: =SUM(C13:C14) -> 0.10932151 | E13: =_xlfn.XLOOKUP($B13, Sheet1!$A$2:$A$20, Sheet1!$B$2:$B$20) -> 0.023789287
B14: Ratio prix de l'immobilier / revenus des ménages | C14: =_xlfn.XLOOKUP($B14, Sheet1!$A$2:$A$20, Sheet1!$D$2:$D$20) -> 0.072071448 | E14: =_xlfn.XLOOKUP($B14, Sheet1!$A$2:$A$20, Sheet1!$B$2:$B$20) -> 0.046027534
A15: Conditions de financement sur les marchés | B15: Spread HY-Mid Swap | C15: =_xlfn.XLOOKUP($B15, Sheet1!$A$2:$A$20, Sheet1!$D$2:$D$20) -> 0.11318862 | D15: =SUM(C15:C18) -> 0.20207913 | E15: =_xlfn.XLOOKUP($B15, Sheet1!$A$2:$A$20, Sheet1!$B$2:$B$20) -> 0.072286504
B16: Spread IG-Mid Swap | C16: =_xlfn.XLOOKUP($B16, Sheet1!$A$2:$A$20, Sheet1!$D$2:$D$20) -> 0.052028917 | E16: =_xlfn.XLOOKUP($B16, Sheet1!$A$2:$A$20, Sheet1!$B$2:$B$20) -> 0.03322762
B17: Spread OAT-Bund | C17: =_xlfn.XLOOKUP($B17, Sheet1!$A$2:$A$20, Sheet1!$D$2:$D$20) -> 0.014377977 | E17: =_xlfn.XLOOKUP($B17, Sheet1!$A$2:$A$20, Sheet1!$B$2:$B$20) -> 0.0091823163
B18: Niveau de rendement souverain à 10 ans | C18: =_xlfn.XLOOKUP($B18, Sheet1!$A$2:$A$20, Sheet1!$D$2:$D$20) -> 0.022483616 | E18: =_xlfn.XLOOKUP($B18, Sheet1!$A$2:$A$20, Sheet1!$B$2:$B$20) -> 0.014358882
A19: Surévaluation sur les marchés | B19: Prime de CDS moyen CAC 40 | C19: =_xlfn.XLOOKUP($B19, Sheet1!$A$2:$A$20, Sheet1!$D$2:$D$20) -> 0.018336698 | D19: =SUM(C19:C20) -> 0.035397246 | E19: =_xlfn.XLOOKUP($B19, Sheet1!$A$2:$A$20, Sheet1!$B$2:$B$20) -> 0.011710504
B20: Price earning ratio | C20: =_xlfn.XLOOKUP($B20, Sheet1!$A$2:$A$20, Sheet1!$D$2:$D$20) -> 0.017060549 | E20: =_xlfn.XLOOKUP($B20, Sheet1!$A$2:$A$20, Sheet1!$B$2:$B$20) -> 0.010895507
