Workbook

Sheet Sheet1
A1: indicator | B1: weight
A2: Ratio dette/PIB des ménages | B2: 0.1658921
A3: Spread HY-Mid Swap | B3: 0.15678096
A4: Croissance des prêts aux ménages | B4: 0.10190756
A5: Debt Service Ratio des SNF | B5: 0.077648838
A6: Debt Service Ratio des ménages | B6: 0.076810263
A7: Ratio dette/PIB des SNF | B7: 0.073572381
A8: Ratio prix de l'immobilier / revenus des ménages | B8: 0.072750477
A9: Croissance des prêts aux SNF | B9: 0.055130944
A10: Surévaluation des prix de l'immobilier (ISPI) | B10: 0.045153952
A11: Taux d'intérêt moyen des nouveaux crédits aux ménages | B11: 0.041748091
A12: Taux d'intérêt moyen des nouveaux crédits aux SNF | B12: 0.034247513
A13: Durcissement des conditions d'octroi du crédit (% soldes d'opinion) – Entreprises (BLS) | B13: 0.02894644
... A18: Prime de CDS moyen CAC 40 | B18: 0.0054381954

Sheet Tableau poids RF
A1: Catégories | B1: Indicateurs | C1: Pondération | D1: Par catégorie | F1: Indicateurs | G1: Pondération
A2: Encours de dette des ménages et SNF | B2: Ratio dette/PIB des ménages | C2: =_xlfn.XLOOKUP('Tableau poids RF'!B2,Sheet1!A:A,Sheet1!B:B) -> 0.1658921 | D2: =SUM(C2:C7) -> 0.55096209 | F2: Ratio dette/PIB des ménages | G2: 0.1658921
B3: Ratio dette/PIB des SNF | C3: =_xlfn.XLOOKUP('Tableau poids RF'!B3,Sheet1!A:A,Sheet1!B:B) -> 0.073572381 | F3: Spread HY-Mid Swap | G3: 0.15678096
B4: Croissance des prêts aux ménages | C4: =_xlfn.XLOOKUP('Tableau poids RF'!B4,Sheet1!A:A,Sheet1!B:B) -> 0.10190756 | F4: Croissance des prêts aux ménages | G4: 0.10190756
B5: Croissance des prêts aux SNF | C5: =_xlfn.XLOOKUP('Tableau poids RF'!B5,Sheet1!A:A,Sheet1!B:B) -> 0.055130944 | F5: Debt Service Ratio des SNF | G5: 0.077648838
B6: Debt Service Ratio des ménages | C6: =_xlfn.XLOOKUP('Tableau poids RF'!B6,Sheet1!A:A,Sheet1!B:B) -> 0.076810263 | F6: Debt Service Ratio des ménages | G6: 0.076810263
B7: Debt Service Ratio des SNF | C7: =_xlfn.XLOOKUP('Tableau poids RF'!B7,Sheet1!A:A,Sheet1!B:B) -> 0.077648838 | F7: Ratio dette/PIB des SNF | G7: 0.073572381
A9: Conditions de financement du crédit | B9: Taux d'intérêt moyen des nouveaux crédits aux ménages | C9: =_xlfn.XLOOKUP('Tableau poids RF'!B9,Sheet1!A:A,Sheet1!B:B) -> 0.041748091 | D9: =SUM(C9:C13) -> 0.14107687 | F9: Ratio prix de l'immobilier / revenus des ménages | G9: 0.072750477
B10: Taux d'intérêt moyen des nouveaux crédits aux SNF | C10: =_xlfn.XLOOKUP('Tableau poids RF'!B10,Sheet1!A:A,Sheet1!B:B) -> 0.034247513 | F10: Croissance des prêts aux SNF | G10: 0.055130944
B11: Durcissement des conditions d'octroi du crédit (% soldes d'opinion) – Entreprises (BLS) | C11: =_xlfn.XLOOKUP('Tableau poids RF'!B11,Sheet1!A:A,Sheet1!B:B) -> 0.02894644 | F11: Surévaluation des prix de l'immobilier (ISPI) | G11: 0.045153952
B12: Durcissement des conditions d'octroi du crédit (% soldes d'opinion) – Ménages (BLS) | C12: =_xlfn.XLOOKUP('Tableau poids RF'!B12,Sheet1!A:A,Sheet1!B:B) -> 0.019263024 | F12: Taux d'intérêt moyen des nouveaux crédits aux ménages | G12: 0.041748091
B13: Part des SNF ayant des "contraintes de crédit" (% de réponses) (SAFE) | C13: =_xlfn.XLOOKUP('Tableau poids RF'!B13,Sheet1!A:A,Sheet1!B:B) -> 0.016871798 | F13: Taux d'intérêt moyen des nouveaux crédits aux SNF | G13: 0.034247513
A15: Marché immobilier | B15: Surévaluation des prix de l'immobilier (ISPI) | C15: =_xlfn.XLOOKUP('Tableau poids RF'!B15,Sheet1!A:A,Sheet1!B:B) -> 0.045153952 | D15: =SUM(C15:C16) -> 0.11790443 | F15: Durcissement des conditions d'octroi du crédit (% soldes d'opinion) – Entreprises (BLS) | G15: 0.02894644
B16: Ratio prix de l'immobilier / revenus des ménages | C16: =_xlfn.XLOOKUP('Tableau poids RF'!B16,Sheet1!A:A,Sheet1!B:B) -> 0.072750477 | F16: Durcissement des conditions d'octroi du crédit (% soldes d'opinion) – Ménages (BLS) | G16: 0.019263024
A18: Conditions de financement sur les marchés | B18: Spread HY-Mid Swap | C18: =_xlfn.XLOOKUP('Tableau poids RF'!B18,Sheet1!A:A,Sheet1!B:B) -> 0.15678096 | D18: =SUM(C18:C19) -> 0.16955711 | F18: Part des SNF ayant des "contraintes de crédit" (% de réponses) (SAFE) | G18: 0.016871798
B19: Spread OAT-Bund | C19: =_xlfn.XLOOKUP('Tableau poids RF'!B19,Sheet1!A:A,Sheet1!B:B) -> 0.012776143 | F19: Price earning ratio | G19: 0.015061309
A21: Surévaluation sur les marchés | B21: Prime de CDS moyen CAC 40 | C21: =_xlfn.XLOOKUP('Tableau poids RF'!B21,Sheet1!A:A,Sheet1!B:B) -> 0.0054381954 | D21: =SUM(C21:C22) -> 0.020499504 | F21: Spread OAT-Bund | G21: 0.012776143
B22: Price earning ratio | C22: =_xlfn.XLOOKUP('Tableau poids RF'!B22,Sheet1!A:A,Sheet1!B:B) -> 0.015061309 | F22: Prime de CDS moyen CAC 40 | G22: 0.0054381954

Sheet Feuil1
A1: Catégories | B1: Indicateurs | C1: Pondération | D1: Par catégorie
A2: Encours de dette des ménages et SNF | B2: Ratio dette/PIB des ménages | C2: 0.1658921 | D2: 0.55096209
B3: Croissance des prêts aux ménages | C3: 0.10190756
B4: Debt Service Ratio des SNF | C4: 0.077648838
B5: Debt Service Ratio des ménages | C5: 0.076810263
B6: Ratio dette/PIB des SNF | C6: 0.073572381
B7: Croissance des prêts aux SNF | C7: 0.055130944
A8: Conditions de financement du crédit | B8: Taux d'intérêt moyen des nouveaux crédits aux ménages | C8: 0.041748091 | D8: 0.14107687
B9: Taux d'intérêt moyen des nouveaux crédits aux SNF | C9: 0.034247513
B10: Durcissement des conditions d'octroi du crédit (% soldes d'opinion) – Entreprises (BLS) | C10: 0.02894644
B11: Durcissement des conditions d'octroi du crédit (% soldes d'opinion) – Ménages (BLS) | C11: 0.019263024
B12: Part des SNF ayant des "contraintes de crédit" (% de réponses) (SAFE) | C12: 0.016871798
A13: Marché immobilier | B13: Ratio prix de l'immobilier / revenus des ménages | C13: 0.072750477 | D13: 0.11790443
B14: Surévaluation des prix de l'immobilier (ISPI) | C14: 0.045153952
A15: Conditions de financement sur les marchés | B15: Spread HY-Mid Swap | C15: 0.15678096 | D15: 0.16955711
B16: Spread OAT-Bund | C16: 0.012776143
A17: Surévaluation sur les marchés | B17: Price earning ratio | C17: 0.015061309 | D17: 0.020499504
B18: Prime de CDS moyen CAC 40 | C18: 0.0054381954
