Workbook

Sheet Sheet1
A1: var | B1: imp | C1: imp_pos | D1: weight
A2: encours_dette_CNFSI_DetteH | B2: 0.088011845 | C2: 0.088011845 | D2: 0.16575923
A3: financement_marche_SPREADHY | B3: 0.082838193 | C3: 0.082838193 | D3: 0.1560153
A4: encours_dette_BSI1_TC_creditH | B4: 0.05336728 | C4: 0.05336728 | D4: 0.10051055
A5: encours_dette_DSR_DSRH | B5: 0.042239463 | C5: 0.042239463 | D5: 0.07955271
A6: encours_dette_DSR_DSRSNF | B6: 0.040737106 | C6: 0.040737106 | D6: 0.076723208
A7: marche_immo_OCDE | B7: 0.039345226 | C7: 0.039345226 | D7: 0.074101778
A8: encours_dette_CNFSI_DetteSNF | B8: 0.039342015 | C8: 0.039342015 | D8: 0.074095731
A9: encours_dette_BSI1_TC_creditSNF | B9: 0.028872789 | C9: 0.028872789 | D9: 0.054378262
A10: marche_immo_ISPI | B10: 0.025125328 | C10: 0.025125328 | D10: 0.047320391
A11: financement_credit_MIR_menages | B11: 0.021810671 | C11: 0.021810671 | D11: 0.041077651
A12: financement_credit_MIR_snf | B12: 0.01805487 | C12: 0.01805487 | D12: 0.034004074
A13: financement_credit_BLS_Entreprises | B13: 0.015048113 | C13: 0.015048113 | D13: 0.028341225
... A18: marche_surrevaluation_CDS | B18: 0.0028669501 | C18: 0.0028669501 | D18: 0.0053995395

Sheet Lag
A1: var | B1: imp | C1: imp_pos | D1: weight
A2: encours_dette_BSI1_TC_creditH | B2: 0.049689529 | C2: 0.049689529 | D2: 0.13702112
A3: encours_dette_CNFSI_DetteH | B3: 0.046113295 | C3: 0.046113295 | D3: 0.12715949
A4: encours_dette_BSI1_TC_creditSNF | B4: 0.041991004 | C4: 0.041991004 | D4: 0.11579209
A5: encours_dette_DSR_DSRSNF | B5: 0.039556519 | C5: 0.039556519 | D5: 0.10907889
A6: encours_dette_DSR_DSRH | B6: 0.038246565 | C6: 0.038246565 | D6: 0.10546663
A7: marche_immo_OCDE | B7: 0.0378604 | C7: 0.0378604 | D7: 0.10440176
A8: encours_dette_CNFSI_DetteSNF | B8: 0.037561739 | C8: 0.037561739 | D8: 0.10357819
A9: financement_credit_MIR_snf | B9: 0.015046673 | C9: 0.015046673 | D9: 0.041491881
A10: financement_credit_MIR_menages | B10: 0.012976406 | C10: 0.012976406 | D10: 0.035783024
A11: financement_marche_SPREADHY | B11: 0.010883549 | C11: 0.010883549 | D11: 0.030011878
A12: marche_immo_ISPI | B12: 0.0076967512 | C12: 0.0076967512 | D12: 0.021224139
A13: financement_marche_SPREAD_OATBD | B13: 0.007577694 | C13: 0.007577694 | D13: 0.020895833
... A18: marche_surrevaluation_CDS | B18: 0.00017460457 | C18: 0.00017460457 | D18: 0.00048147999

Sheet Lag 2
A1: var | B1: imp | C1: imp_pos | D1: weight
A2: encours_dette_CNFSI_DetteH | B2: 0.067779391 | C2: 0.067779391 | D2: 0.13195821
A3: encours_dette_CNFSI_DetteSNF | B3: 0.062366231 | C3: 0.062366231 | D3: 0.12141945
A4: encours_dette_BSI1_TC_creditH | B4: 0.060191442 | C4: 0.060191442 | D4: 0.1171854
A5: financement_marche_SPREADHY | B5: 0.0544168 | C5: 0.0544168 | D5: 0.10594288
A6: encours_dette_DSR_DSRSNF | B6: 0.044475492 | C6: 0.044475492 | D6: 0.086588362
A7: marche_immo_OCDE | B7: 0.043944153 | C7: 0.043944153 | D7: 0.085553911
A8: encours_dette_DSR_DSRH | B8: 0.030756557 | C8: 0.030756557 | D8: 0.059879268
A9: financement_credit_MIR_menages | B9: 0.030046029 | C9: 0.030046029 | D9: 0.058495956
A10: encours_dette_BSI1_TC_creditSNF | B10: 0.027445164 | C10: 0.027445164 | D10: 0.053432389
A11: financement_credit_MIR_snf | B11: 0.016724263 | C11: 0.016724263 | D11: 0.032560103
A12: marche_surrevaluation_PER | B12: 0.016659118 | C12: 0.016659118 | D12: 0.032433272
A13: financement_credit_BLS_Menages | B13: 0.015878716 | C13: 0.015878716 | D13: 0.030913925
... A18: financement_credit_BLS_Entreprises | B18: 0.0051227968 | C18: 0.0051227968 | D18: 0.009973461

Sheet Tableau
A1: Catégories | B1: Indicateurs | C1: Pondération | D1: Par catégorie | G1: Pondération laggée
A2: Encours de dette des ménages et SNF | B2: Ratio dette/PIB des ménages | C2: 0.16575923 | D2: =SUM(C2:C7) -> 0.55101969 | E2: encours_dette_CNFSI_DetteH | G2: =_xlfn.XLOOKUP(E2,Lag!A:A,Lag!D:D) -> 0.12715949
B3: Croissance des prêts aux ménages | C3: 0.10051055 | E3: encours_dette_CNFSI_DetteSNF | G3: =_xlfn.XLOOKUP(E3,Lag!A:A,Lag!D:D) -> 0.10357819
B4: Debt Service Ratio des ménages | C4: 0.07955271 | E4: encours_dette_BSI1_TC_creditH | G4: =_xlfn.XLOOKUP(E4,Lag!A:A,Lag!D:D) -> 0.13702112
B5: Debt Service Ratio des SNF | C5: 0.076723208 | E5: encours_dette_BSI1_TC_creditSNF | G5: =_xlfn.XLOOKUP(E5,Lag!A:A,Lag!D:D) -> 0.11579209
B6: Ratio dette/PIB des SNF | C6: 0.074095731 | E6: encours_dette_DSR_DSRH | G6: =_xlfn.XLOOKUP(E6,Lag!A:A,Lag!D:D) -> 0.10546663
B7: Croissance des prêts aux SNF | C7: 0.054378262 | E7: encours_dette_DSR_DSRSNF | G7: =_xlfn.XLOOKUP(E7,Lag!A:A,Lag!D:D) -> 0.10907889
A8: Conditions de financement du crédit | B8: Taux d'intérêt moyen des nouveaux crédits aux ménages | C8: 0.041077651 | D8: =SUM(C8:C12) -> 0.13860337 | E8: financement_credit_MIR_menages | G8: =_xlfn.XLOOKUP(E8,Lag!A:A,Lag!D:D) -> 0.035783024
B9: Taux d'intérêt moyen des nouveaux crédits aux SNF | C9: 0.034004074 | E9: financement_credit_MIR_snf | G9: =_xlfn.XLOOKUP(E9,Lag!A:A,Lag!D:D) -> 0.041491881
B10: Durcissement des conditions d'octroi du crédit (% soldes d'opinion) – Entreprises (BLS) | C10: 0.028341225 | E10: financement_credit_BLS_Entreprises | G10: =_xlfn.XLOOKUP(E10,Lag!A:A,Lag!D:D) -> 0.019557844
B11: Durcissement des conditions d'octroi du crédit (% soldes d'opinion) – Ménages (BLS) | C11: 0.019126099 | E11: financement_credit_BLS_Menages | G11: =_xlfn.XLOOKUP(E11,Lag!A:A,Lag!D:D) -> 0.01209934
B12: Part des SNF ayant des "contraintes de crédit" (% de réponses) (SAFE) | C12: 0.016054323 | E12: financement_credit_SAFE | G12: =_xlfn.XLOOKUP(E12,Lag!A:A,Lag!D:D) -> 0.01369047
A13: Marché immobilier | B13: Ratio prix de l'immobilier / revenus des ménages | C13: 0.074101778 | D13: =SUM(C13:C14) -> 0.12142217 | E13: marche_immo_ISPI | G13: =_xlfn.XLOOKUP(E13,Lag!A:A,Lag!D:D) -> 0.021224139
B14: Surévaluation des prix de l'immobilier (ISPI) | C14: 0.047320391 | E14: marche_immo_OCDE | G14: =_xlfn.XLOOKUP(E14,Lag!A:A,Lag!D:D) -> 0.10440176
A15: Conditions de financement sur les marchés | B15: Spread HY-Mid Swap | C15: 0.1560153 | D15: =SUM(C15:C16) -> 0.16680729 | E15: financement_marche_SPREADHY | G15: =_xlfn.XLOOKUP(E15,Lag!A:A,Lag!D:D) -> 0.030011878
B16: Spread OAT-Bund | C16: 0.010791988 | E16: financement_marche_SPREAD_OATBD | G16: =_xlfn.XLOOKUP(E16,Lag!A:A,Lag!D:D) -> 0.020895833
A17: Surévaluation sur les marchés | B17: Price earning ratio | C17: 0.016747939 | D17: =SUM(C17:C18) -> 0.022147479 | E17: marche_surrevaluation_PER | G17: =_xlfn.XLOOKUP(E17,Lag!A:A,Lag!D:D) -> 0.0022659388
B18: Prime de CDS moyen CAC 40 | C18: 0.0053995395 | E18: marche_surrevaluation_CDS | G18: =_xlfn.XLOOKUP(E18,Lag!A:A,Lag!D:D) -> 0.00048147999
C20: =SUM(C2:C18) -> 1 | D20: =SUM(D2:D18) -> 1
A22: Catégories | B22: Indicateurs | C22: Pondération | D22: Par catégorie | E22: Pondération laggée | F22: Par catégorie (laggée) | G22: Pondération laggée | H22: Par catégorie (laggée)
A23: Encours de dette des ménages et SNF | B23: Ratio dette/PIB des ménages | C23: 0.166 | D23: =SUM(C23:C28) -> 0.552 | E23: 0.12715949 | F23: =SUM(E23:E28) -> 0.69809641 | G23: 0.13195821 | H23: 0.57046308
B24: Croissance des prêts aux ménages | C24: 0.101 | E24: 0.10357819 | G24: 0.12141945
B25: Debt Service Ratio des ménages | C25: 0.08 | E25: 0.13702112 | G25: 0.1171854
B26: Debt Service Ratio des SNF | C26: 0.077 | E26: 0.11579209 | G26: 0.053432389
B27: Ratio dette/PIB des SNF | C27: 0.074 | E27: 0.10546663 | G27: 0.059879268
B28: Croissance des prêts aux SNF | C28: 0.054 | E28: 0.10907889 | G28: 0.086588362
A29: Conditions de financement du crédit | B29: Taux d'intérêt moyen des nouveaux crédits aux ménages | C29: 0.041 | D29: =SUM(C29:C33) -> 0.138 | E29: 0.035783024 | F29: =SUM(E29:E33) -> 0.12262256 | G29: 0.058495956 | H29: 0.14781615
B30: Taux d'intérêt moyen des nouveaux crédits aux SNF | C30: 0.034 | E30: 0.041491881 | G30: 0.032560103
B31: Durcissement des conditions d'octroi du crédit (% soldes d'opinion) – Entreprises (BLS) | C31: 0.028 | E31: 0.019557844 | G31: 0.009973461
B32: Durcissement des conditions d'octroi du crédit (% soldes d'opinion) – Ménages (BLS) | C32: 0.019 | E32: 0.01209934 | G32: 0.030913925
B33: Part des SNF ayant des "contraintes de crédit" (% de réponses) (SAFE) | C33: 0.016 | E33: 0.01369047 | G33: 0.015872707
A34: Marché immobilier | B34: Ratio prix de l'immobilier / revenus des ménages | C34: 0.074 | D34: =SUM(C34:C35) -> 0.121 | E34: 0.021224139 | F34: =SUM(E34:E35) -> 0.1256259 | G34: 0.019420756 | H34: 0.10497467
B35: Surévaluation des prix de l'immobilier (ISPI) | C35: 0.047 | E35: 0.10440176 | G35: 0.085553911
A36: Conditions de financement sur les marchés | B36: Spread HY-Mid Swap | C36: 0.156 | D36: =SUM(C36:C37) -> 0.167 | E36: 0.030011878 | F36: =SUM(E36:E37) -> 0.050907711 | G36: 0.10594288 | H36: 0.12674557
B37: Spread OAT-Bund | C37: 0.011 | E37: 0.020895833 | G37: 0.02080269
A38: Surévaluation sur les marchés | B38: Price earning ratio | C38: 0.017 | D38: =SUM(C38:C39) -> 0.022 | E38: 0.0022659388 | F38: =SUM(E38:E39) -> 0.0027474188 | G38: 0.032433272 | H38: 0.050000529
B39: Prime de CDS moyen CAC 40 | C39: 0.005 | E39: 0.00048147999 | G39: 0.017567257
